hazus/__init__.py
hazus/__main__.py
hazus/common/__init__.py
hazus/common/classes.py
hazus/common/methods.py
hazus/earthquake/__init__.py
hazus/earthquake/classes.py
hazus/earthquake/modules/AEBM.py
hazus/earthquake/modules/__init__.py
hazus/earthquake/modules/advanced_engineering_bldg_mode.py
hazus/earthquake/modules/direct_social_losses.py
hazus/earthquake/modules/essential_facilities.py
hazus/earthquake/modules/general_buildings.py
hazus/earthquake/modules/indirect_economic_loss.py
hazus/earthquake/modules/induced_physical_damage.py
hazus/earthquake/modules/military_installation.py
hazus/earthquake/modules/transportation_systems.py
hazus/earthquake/modules/user_defined_structures.py
hazus/earthquake/modules/utility_systems.py
hazus/flood/__init__.py
hazus/flood/classes.py
hazus/flood/modules/UDF.py
hazus/flood/modules/__init__.py
hazus/flood/modules/agriculture.py
hazus/flood/modules/direct_social_losses.py
hazus/flood/modules/essential_facilities.py
hazus/flood/modules/general_building_stock.py
hazus/flood/modules/indirect_economic_loss.py
hazus/flood/modules/transportation_systems.py
hazus/flood/modules/user_defined_structures.py
hazus/flood/modules/utility_systems.py
hazus/flood/modules/vehicles.py
hazus/flood/modules/what_if.py
hazus/hurricane/__init__.py
hazus/hurricane/classes.py
hazus/hurricane/modules/__init__.py
hazus/hurricane/modules/direct_economic_loss.py
hazus/hurricane/modules/direct_physical_damage.py
hazus/hurricane/modules/direct_social_loss.py
hazus/hurricane/modules/induced_physical_damage.py
hazus/legacy/__init__.py
hazus/legacy/common.py
hazus/legacy/exporting/Setup_Connection.py
hazus/legacy/exporting/__init__.py
hazus/legacy/exporting/classes.py
hazus/legacy/exporting/methods.py
hazus/legacy/exporting/reports/Eq_Report_Generator.py
hazus/legacy/exporting/reports/Fl_Report_Generator.py
hazus/legacy/exporting/reports/Hu_Report_Generator.py
hazus/legacy/exporting/reports/Ts_Report_Generator.py
hazus/legacy/exporting/reports/__init__.py
hazus-0.0.10.dist-info/LICENSE
hazus-0.0.10.dist-info/METADATA
hazus-0.0.10.dist-info/WHEEL
hazus-0.0.10.dist-info/top_level.txt
hazus-0.0.10.dist-info/RECORD
