Metadata-Version: 2.1
Name: hazus
Version: 0.0.10
Summary: FEMA - Hazus Open-Source Library
Home-page: https://github.com/nhrap-hazus/hazus.git
Author: James Raines
Author-email: james.rainesii@fema.dhs.gov,usharma@niyamit.com
License: UNKNOWN
Platform: UNKNOWN
Classifier: Programming Language :: Python :: 3
Classifier: License :: OSI Approved :: GNU General Public License v3 or later (GPLv3+)
Classifier: Operating System :: OS Independent
Requires-Python: >=3.6
